{
    "0": {
        "3082O00064P0_3082O00006C0": {
            "weekday_evening_peak": {
                "avg_time_sec": 28,
                "data_points": 13611
            },
            "weekday_offpeak": {
                "avg_time_sec": 20,
                "data_points": 13847
            },
            "weekday_morning_peak": {
                "avg_time_sec": 29,
                "data_points": 11332
            },
            "weekday_day": {
                "avg_time_sec": 24,
                "data_points": 11564
            },
            "weekend": {
                "avg_time_sec": 11,
                "data_points": 24995
            }
        },
        "3082O00006C0_3082O00007C0": {
            "weekday_evening_peak": {
                "avg_time_sec": 29,
                "data_points": 711
            },
            "weekday_day": {
                "avg_time_sec": 29,
                "data_points": 2562
            },
            "weekday_morning_peak": {
                "avg_time_sec": 29,
                "data_points": 714
            },
            "weekday_offpeak": {
                "avg_time_sec": 29,
                "data_points": 719
            },
            "weekend": {
                "avg_time_sec": 29,
                "data_points": 2277
            }
        },
        "3082O00007C0_3082O00011C0": {
            "weekday_evening_peak": {
                "avg_time_sec": 29,
                "data_points": 254
            },
            "weekday_offpeak": {
                "avg_time_sec": 28,
                "data_points": 80
            },
            "weekday_day": {
                "avg_time_sec": 29,
                "data_points": 551
            },
            "weekday_morning_peak": {
                "avg_time_sec": 29,
                "data_points": 345
            },
            "weekend": {
                "avg_time_sec": 29,
                "data_points": 327
            }
        },
        "3082O00011C0_3082O00012C0": {
            "weekday_evening_peak": {
                "avg_time_sec": 33,
                "data_points": 279
            },
            "weekday_offpeak": {
                "avg_time_sec": 25,
                "data_points": 32
            },
            "weekday_day": {
                "avg_time_sec": 30,
                "data_points": 580
            },
            "weekday_morning_peak": {
                "avg_time_sec": 30,
                "data_points": 619
            },
            "weekend": {
                "avg_time_sec": 30,
                "data_points": 286
            }
        },
        "3082O00012C0_3082OY0028C9": {
            "weekday_evening_peak": {
                "avg_time_sec": 29,
                "data_points": 633
            },
            "weekday_offpeak": {
                "avg_time_sec": 25,
                "data_points": 66
            },
            "weekday_morning_peak": {
                "avg_time_sec": 29,
                "data_points": 1055
            },
            "weekday_day": {
                "avg_time_sec": 28,
                "data_points": 599
            },
            "weekend": {
                "avg_time_sec": 29,
                "data_points": 317
            }
        },
        "3082OY0028C9_3080O00015C0": {
            "weekday_evening_peak": {
                "avg_time_sec": 30,
                "data_points": 619
            },
            "weekday_offpeak": {
                "avg_time_sec": 35,
                "data_points": 72
            },
            "weekday_day": {
                "avg_time_sec": 31,
                "data_points": 616
            },
            "weekday_morning_peak": {
                "avg_time_sec": 30,
                "data_points": 1048
            },
            "weekend": {
                "avg_time_sec": 30,
                "data_points": 331
            }
        },
        "3082O00029C0_3080O00006C0": {
            "weekday_evening_peak": {
                "avg_time_sec": 30,
                "data_points": 588
            },
            "weekday_offpeak": {
                "avg_time_sec": 27,
                "data_points": 101
            },
            "weekday_morning_peak": {
                "avg_time_sec": 29,
                "data_points": 936
            },
            "weekday_day": {
                "avg_time_sec": 28,
                "data_points": 622
            },
            "weekend": {
                "avg_time_sec": 30,
                "data_points": 528
            }
        },
        "3080O00006C0_3080O00018C0": {
            "weekday_evening_peak": {
                "avg_time_sec": 30,
                "data_points": 580
            },
            "weekday_offpeak": {
                "avg_time_sec": 31,
                "data_points": 97
            },
            "weekday_day": {
                "avg_time_sec": 30,
                "data_points": 614
            },
            "weekday_morning_peak": {
                "avg_time_sec": 30,
                "data_points": 923
            },
            "weekend": {
                "avg_time_sec": 30,
                "data_points": 514
            }
        },
        "3080O00018C0_3080O00013C0": {
            "weekday_evening_peak": {
                "avg_time_sec": 32,
                "data_points": 468
            },
            "weekday_offpeak": {
                "avg_time_sec": 55,
                "data_points": 216
            },
            "weekday_morning_peak": {
                "avg_time_sec": 32,
                "data_points": 1324
            },
            "weekday_day": {
                "avg_time_sec": 45,
                "data_points": 718
            },
            "weekend": {
                "avg_time_sec": 41,
                "data_points": 523
            }
        },
        "3080O00013C0_3056O00021C0": {
            "weekday_evening_peak": {
                "avg_time_sec": 34,
                "data_points": 461
            },
            "weekday_offpeak": {
                "avg_time_sec": 30,
                "data_points": 118
            },
            "weekday_morning_peak": {
                "avg_time_sec": 30,
                "data_points": 1442
            },
            "weekday_day": {
                "avg_time_sec": 30,
                "data_points": 711
            },
            "weekend": {
                "avg_time_sec": 32,
                "data_points": 93
            }
        },
        "3056O00024C0_3056O00005C0": {
            "weekday_evening_peak": {
                "avg_time_sec": 39,
                "data_points": 470
            },
            "weekday_offpeak": {
                "avg_time_sec": 36,
                "data_points": 459
            },
            "weekday_day": {
                "avg_time_sec": 34,
                "data_points": 889
            },
            "weekday_morning_peak": {
                "avg_time_sec": 30,
                "data_points": 1422
            },
            "weekend": {
                "avg_time_sec": 30,
                "data_points": 547
            }
        },
        "3056O00005C0_3071O00034C0": {
            "weekday_evening_peak": {
                "avg_time_sec": 30,
                "data_points": 674
            },
            "weekday_offpeak": {
                "avg_time_sec": 30,
                "data_points": 304
            },
            "weekday_day": {
                "avg_time_sec": 30,
                "data_points": 912
            },
            "weekday_morning_peak": {
                "avg_time_sec": 31,
                "data_points": 1691
            },
            "weekend": {
                "avg_time_sec": 30,
                "data_points": 574
            }
        },
        "3071O00034C0_3071O00009C0": {
            "weekday_evening_peak": {
                "avg_time_sec": 35,
                "data_points": 678
            },
            "weekday_offpeak": {
                "avg_time_sec": 51,
                "data_points": 290
            },
            "weekday_day": {
                "avg_time_sec": 33,
                "data_points": 956
            },
            "weekday_morning_peak": {
                "avg_time_sec": 65,
                "data_points": 1654
            },
            "weekend": {
                "avg_time_sec": 39,
                "data_points": 588
            }
        },
        "3071O00009C0_3071O00010C0": {
            "weekday_evening_peak": {
                "avg_time_sec": 30,
                "data_points": 693
            },
            "weekday_offpeak": {
                "avg_time_sec": 39,
                "data_points": 290
            },
            "weekday_day": {
                "avg_time_sec": 30,
                "data_points": 887
            },
            "weekday_morning_peak": {
                "avg_time_sec": 30,
                "data_points": 1626
            },
            "weekend": {
                "avg_time_sec": 29,
                "data_points": 437
            }
        },
        "3071O00011C0_3071O00035C0": {
            "weekday_evening_peak": {
                "avg_time_sec": 29,
                "data_points": 663
            },
            "weekday_offpeak": {
                "avg_time_sec": 23,
                "data_points": 64
            },
            "weekday_morning_peak": {
                "avg_time_sec": 29,
                "data_points": 1269
            },
            "weekday_day": {
                "avg_time_sec": 28,
                "data_points": 930
            },
            "weekend": {
                "avg_time_sec": 29,
                "data_points": 387
            }
        },
        "3071O00012C0_3071O00013C0": {
            "weekday_evening_peak": {
                "avg_time_sec": 30,
                "data_points": 1174
            },
            "weekday_offpeak": {
                "avg_time_sec": 30,
                "data_points": 460
            },
            "weekday_day": {
                "avg_time_sec": 33,
                "data_points": 1136
            },
            "weekday_morning_peak": {
                "avg_time_sec": 30,
                "data_points": 2055
            },
            "weekend": {
                "avg_time_sec": 30,
                "data_points": 1230
            }
        },
        "3071O00013C0_3071O00031C0": {
            "weekday_evening_peak": {
                "avg_time_sec": 32,
                "data_points": 1137
            },
            "weekday_offpeak": {
                "avg_time_sec": 49,
                "data_points": 479
            },
            "weekday_day": {
                "avg_time_sec": 50,
                "data_points": 1148
            },
            "weekday_morning_peak": {
                "avg_time_sec": 45,
                "data_points": 2263
            },
            "weekend": {
                "avg_time_sec": 30,
                "data_points": 1319
            }
        },
        "3071O00031C0_3070O00011C0": {
            "weekday_evening_peak": {
                "avg_time_sec": 30,
                "data_points": 1235
            },
            "weekday_offpeak": {
                "avg_time_sec": 30,
                "data_points": 656
            },
            "weekday_day": {
                "avg_time_sec": 30,
                "data_points": 1197
            },
            "weekday_morning_peak": {
                "avg_time_sec": 30,
                "data_points": 2569
            },
            "weekend": {
                "avg_time_sec": 30,
                "data_points": 1726
            }
        },
        "3070O00011C0_3070O00003C0": {
            "weekday_evening_peak": {
                "avg_time_sec": 103,
                "data_points": 1187
            },
            "weekday_offpeak": {
                "avg_time_sec": 93,
                "data_points": 766
            },
            "weekday_day": {
                "avg_time_sec": 134,
                "data_points": 1164
            },
            "weekday_morning_peak": {
                "avg_time_sec": 107,
                "data_points": 2740
            },
            "weekend": {
                "avg_time_sec": 83,
                "data_points": 1836
            }
        },
        "3070O00003C0_3070O00004C0": {
            "weekday_evening_peak": {
                "avg_time_sec": 32,
                "data_points": 1459
            },
            "weekday_offpeak": {
                "avg_time_sec": 30,
                "data_points": 974
            },
            "weekday_day": {
                "avg_time_sec": 31,
                "data_points": 1454
            },
            "weekday_morning_peak": {
                "avg_time_sec": 30,
                "data_points": 3032
            },
            "weekend": {
                "avg_time_sec": 30,
                "data_points": 2442
            }
        },
        "3070O00004C0_3068O00001C0": {
            "weekday_evening_peak": {
                "avg_time_sec": 63,
                "data_points": 1412
            },
            "weekday_offpeak": {
                "avg_time_sec": 48,
                "data_points": 893
            },
            "weekday_day": {
                "avg_time_sec": 60,
                "data_points": 1416
            },
            "weekday_morning_peak": {
                "avg_time_sec": 60,
                "data_points": 2923
            },
            "weekend": {
                "avg_time_sec": 52,
                "data_points": 2346
            }
        },
        "3068O00001C0_3068O00002C0": {
            "weekday_evening_peak": {
                "avg_time_sec": 30,
                "data_points": 1566
            },
            "weekday_offpeak": {
                "avg_time_sec": 29,
                "data_points": 979
            },
            "weekday_day": {
                "avg_time_sec": 30,
                "data_points": 1588
            },
            "weekday_morning_peak": {
                "avg_time_sec": 30,
                "data_points": 3076
            },
            "weekend": {
                "avg_time_sec": 30,
                "data_points": 2928
            }
        },
        "3068O00002C0_3068O00003C0": {
            "weekday_evening_peak": {
                "avg_time_sec": 32,
                "data_points": 1551
            },
            "weekday_offpeak": {
                "avg_time_sec": 30,
                "data_points": 849
            },
            "weekday_day": {
                "avg_time_sec": 30,
                "data_points": 1623
            },
            "weekday_morning_peak": {
                "avg_time_sec": 29,
                "data_points": 3093
            },
            "weekend": {
                "avg_time_sec": 30,
                "data_points": 3014
            }
        },
        "3068O00004C0_3066O00002C9": {
            "weekday_evening_peak": {
                "avg_time_sec": 114,
                "data_points": 1
            },
            "weekday_day": {
                "avg_time_sec": 60,
                "data_points": 1
            },
            "weekday_morning_peak": {
                "avg_time_sec": 60,
                "data_points": 1
            },
            "weekday_offpeak": {
                "avg_time_sec": 62,
                "data_points": 1
            },
            "weekend": {
                "avg_time_sec": 61,
                "data_points": 1
            }
        },
        "3066O00007C9_3066O00008C9": {
            "weekday_evening_peak": {
                "avg_time_sec": 30,
                "data_points": 3033
            },
            "weekday_morning_peak": {
                "avg_time_sec": 30,
                "data_points": 1293
            },
            "weekday_day": {
                "avg_time_sec": 30,
                "data_points": 6335
            },
            "weekend": {
                "avg_time_sec": 30,
                "data_points": 7247
            },
            "weekday_offpeak": {
                "avg_time_sec": 30,
                "data_points": 7139
            }
        },
        "3066O00008C9_3066O00010C9": {
            "weekday_evening_peak": {
                "avg_time_sec": 29,
                "data_points": 3239
            },
            "weekday_morning_peak": {
                "avg_time_sec": 30,
                "data_points": 1290
            },
            "weekday_day": {
                "avg_time_sec": 30,
                "data_points": 6427
            },
            "weekend": {
                "avg_time_sec": 29,
                "data_points": 7919
            },
            "weekday_offpeak": {
                "avg_time_sec": 29,
                "data_points": 7431
            }
        },
        "3066O00010C9_3066O00011C9": {
            "weekday_evening_peak": {
                "avg_time_sec": 33,
                "data_points": 3725
            },
            "weekday_morning_peak": {
                "avg_time_sec": 39,
                "data_points": 1584
            },
            "weekday_day": {
                "avg_time_sec": 34,
                "data_points": 7335
            },
            "weekend": {
                "avg_time_sec": 30,
                "data_points": 9945
            },
            "weekday_offpeak": {
                "avg_time_sec": 30,
                "data_points": 9485
            }
        },
        "3066O00011C9_3066O00051C0": {
            "weekday_evening_peak": {
                "avg_time_sec": 43,
                "data_points": 3581
            },
            "weekday_morning_peak": {
                "avg_time_sec": 40,
                "data_points": 1410
            },
            "weekday_day": {
                "avg_time_sec": 44,
                "data_points": 6963
            },
            "weekend": {
                "avg_time_sec": 30,
                "data_points": 8487
            },
            "weekday_offpeak": {
                "avg_time_sec": 30,
                "data_points": 7846
            }
        },
        "3066O00051C0_3066O00012C0": {
            "weekday_evening_peak": {
                "avg_time_sec": 29,
                "data_points": 1789
            },
            "weekday_morning_peak": {
                "avg_time_sec": 29,
                "data_points": 711
            },
            "weekday_day": {
                "avg_time_sec": 29,
                "data_points": 3851
            },
            "weekend": {
                "avg_time_sec": 29,
                "data_points": 4628
            },
            "weekday_offpeak": {
                "avg_time_sec": 29,
                "data_points": 3928
            }
        },
        "3066O00012C0_3068O00017C0": {
            "weekday_evening_peak": {
                "avg_time_sec": 30,
                "data_points": 2220
            },
            "weekday_morning_peak": {
                "avg_time_sec": 30,
                "data_points": 926
            },
            "weekday_day": {
                "avg_time_sec": 30,
                "data_points": 4788
            },
            "weekday_offpeak": {
                "avg_time_sec": 30,
                "data_points": 6210
            },
            "weekend": {
                "avg_time_sec": 30,
                "data_points": 6413
            }
        },
        "3068O00017C0_3068O00018C0": {
            "weekday_evening_peak": {
                "avg_time_sec": 30,
                "data_points": 3980
            },
            "weekday_morning_peak": {
                "avg_time_sec": 30,
                "data_points": 1433
            },
            "weekday_day": {
                "avg_time_sec": 30,
                "data_points": 8112
            },
            "weekday_offpeak": {
                "avg_time_sec": 29,
                "data_points": 9301
            },
            "weekend": {
                "avg_time_sec": 29,
                "data_points": 10997
            }
        },
        "3068O00018C0_3068O00019C0": {
            "weekday_evening_peak": {
                "avg_time_sec": 30,
                "data_points": 4256
            },
            "weekday_morning_peak": {
                "avg_time_sec": 30,
                "data_points": 1539
            },
            "weekday_day": {
                "avg_time_sec": 30,
                "data_points": 6957
            },
            "weekday_offpeak": {
                "avg_time_sec": 29,
                "data_points": 8987
            },
            "weekend": {
                "avg_time_sec": 29,
                "data_points": 9734
            }
        },
        "3068O00019C0_3068O00007C0": {
            "weekday_evening_peak": {
                "avg_time_sec": 29,
                "data_points": 4287
            },
            "weekday_morning_peak": {
                "avg_time_sec": 30,
                "data_points": 1574
            },
            "weekday_day": {
                "avg_time_sec": 29,
                "data_points": 7230
            },
            "weekday_offpeak": {
                "avg_time_sec": 30,
                "data_points": 9977
            },
            "weekend": {
                "avg_time_sec": 27,
                "data_points": 10140
            }
        },
        "3068O00007C0_3067O00012C0": {
            "weekday_evening_peak": {
                "avg_time_sec": 46,
                "data_points": 4525
            },
            "weekday_morning_peak": {
                "avg_time_sec": 72,
                "data_points": 1789
            },
            "weekday_day": {
                "avg_time_sec": 39,
                "data_points": 8929
            },
            "weekday_offpeak": {
                "avg_time_sec": 30,
                "data_points": 12560
            },
            "weekend": {
                "avg_time_sec": 30,
                "data_points": 12239
            }
        },
        "3067O00012C0_3067O00001C0": {
            "weekday_evening_peak": {
                "avg_time_sec": 29,
                "data_points": 3700
            },
            "weekday_morning_peak": {
                "avg_time_sec": 29,
                "data_points": 1465
            },
            "weekday_day": {
                "avg_time_sec": 29,
                "data_points": 7672
            },
            "weekday_offpeak": {
                "avg_time_sec": 29,
                "data_points": 9082
            },
            "weekend": {
                "avg_time_sec": 28,
                "data_points": 8533
            }
        },
        "3067O00002C0_3067O00003C0": {
            "weekday_evening_peak": {
                "avg_time_sec": 29,
                "data_points": 4168
            },
            "weekday_morning_peak": {
                "avg_time_sec": 28,
                "data_points": 1316
            },
            "weekday_day": {
                "avg_time_sec": 29,
                "data_points": 8430
            },
            "weekday_offpeak": {
                "avg_time_sec": 29,
                "data_points": 7013
            },
            "weekend": {
                "avg_time_sec": 27,
                "data_points": 8345
            }
        },
        "3067O00003C0_3069O00004C0": {
            "weekday_evening_peak": {
                "avg_time_sec": 29,
                "data_points": 3149
            },
            "weekday_morning_peak": {
                "avg_time_sec": 28,
                "data_points": 873
            },
            "weekday_day": {
                "avg_time_sec": 29,
                "data_points": 6171
            },
            "weekday_offpeak": {
                "avg_time_sec": 29,
                "data_points": 3699
            },
            "weekend": {
                "avg_time_sec": 27,
                "data_points": 4409
            }
        },
        "3069O00004C0_3069O00005C0": {
            "weekday_evening_peak": {
                "avg_time_sec": 30,
                "data_points": 3265
            },
            "weekday_morning_peak": {
                "avg_time_sec": 30,
                "data_points": 1274
            },
            "weekday_day": {
                "avg_time_sec": 30,
                "data_points": 6724
            },
            "weekday_offpeak": {
                "avg_time_sec": 30,
                "data_points": 8215
            },
            "weekend": {
                "avg_time_sec": 29,
                "data_points": 7528
            }
        },
        "3069O00005C0_3069O00006C0": {
            "weekday_evening_peak": {
                "avg_time_sec": 30,
                "data_points": 4650
            },
            "weekday_morning_peak": {
                "avg_time_sec": 29,
                "data_points": 1857
            },
            "weekday_day": {
                "avg_time_sec": 29,
                "data_points": 9281
            },
            "weekday_offpeak": {
                "avg_time_sec": 30,
                "data_points": 13931
            },
            "weekend": {
                "avg_time_sec": 29,
                "data_points": 13254
            }
        },
        "3069O00006C0_3069O00048C0": {
            "weekday_evening_peak": {
                "avg_time_sec": 29,
                "data_points": 4923
            },
            "weekday_morning_peak": {
                "avg_time_sec": 29,
                "data_points": 1817
            },
            "weekday_day": {
                "avg_time_sec": 26,
                "data_points": 9252
            },
            "weekday_offpeak": {
                "avg_time_sec": 29,
                "data_points": 14156
            },
            "weekend": {
                "avg_time_sec": 29,
                "data_points": 12857
            }
        },
        "3069O00049C0_3069O00052C0": {
            "weekday_evening_peak": {
                "avg_time_sec": 32,
                "data_points": 5221
            },
            "weekday_morning_peak": {
                "avg_time_sec": 40,
                "data_points": 1840
            },
            "weekday_day": {
                "avg_time_sec": 30,
                "data_points": 9834
            },
            "weekday_offpeak": {
                "avg_time_sec": 30,
                "data_points": 14168
            },
            "weekend": {
                "avg_time_sec": 30,
                "data_points": 13609
            }
        },
        "3069O00052C0_3069O00029C0": {
            "weekday_evening_peak": {
                "avg_time_sec": 30,
                "data_points": 5303
            },
            "weekday_morning_peak": {
                "avg_time_sec": 30,
                "data_points": 1847
            },
            "weekday_day": {
                "avg_time_sec": 29,
                "data_points": 9878
            },
            "weekday_offpeak": {
                "avg_time_sec": 30,
                "data_points": 14158
            },
            "weekend": {
                "avg_time_sec": 30,
                "data_points": 14131
            }
        },
        "3069O00030C0_3069O00031C0": {
            "weekday_evening_peak": {
                "avg_time_sec": 30,
                "data_points": 4239
            },
            "weekday_morning_peak": {
                "avg_time_sec": 31,
                "data_points": 1755
            },
            "weekday_day": {
                "avg_time_sec": 30,
                "data_points": 8545
            },
            "weekday_offpeak": {
                "avg_time_sec": 30,
                "data_points": 9900
            },
            "weekend": {
                "avg_time_sec": 30,
                "data_points": 10926
            }
        },
        "3069O00031C0_3079O00034C0": {
            "weekday_evening_peak": {
                "avg_time_sec": 30,
                "data_points": 3981
            },
            "weekday_morning_peak": {
                "avg_time_sec": 30,
                "data_points": 1665
            },
            "weekday_day": {
                "avg_time_sec": 30,
                "data_points": 7823
            },
            "weekday_offpeak": {
                "avg_time_sec": 29,
                "data_points": 10324
            },
            "weekend": {
                "avg_time_sec": 29,
                "data_points": 10274
            }
        },
        "3079O00034C0_p35k": {
            "weekday_evening_peak": {
                "avg_time_sec": 30,
                "data_points": 5552
            },
            "weekday_morning_peak": {
                "avg_time_sec": 30,
                "data_points": 1839
            },
            "weekday_day": {
                "avg_time_sec": 29,
                "data_points": 9120
            },
            "weekday_offpeak": {
                "avg_time_sec": 30,
                "data_points": 14371
            },
            "weekend": {
                "avg_time_sec": 30,
                "data_points": 13353
            }
        },
        "p35k_3079O00035C0": {
            "weekday_evening_peak": {
                "avg_time_sec": 30,
                "data_points": 1
            }
        },
        "3079O00019C0_3082O00046C0": {
            "weekday_evening_peak": {
                "avg_time_sec": 29,
                "data_points": 2
            },
            "weekday_morning_peak": {
                "avg_time_sec": 21,
                "data_points": 2
            },
            "weekday_day": {
                "avg_time_sec": 28,
                "data_points": 29
            },
            "weekday_offpeak": {
                "avg_time_sec": 20,
                "data_points": 1
            },
            "weekend": {
                "avg_time_sec": 15,
                "data_points": 2
            }
        },
        "3082O00046C0_3082O00047C0": {
            "weekday_evening_peak": {
                "avg_time_sec": 30,
                "data_points": 6557
            },
            "weekday_morning_peak": {
                "avg_time_sec": 36,
                "data_points": 2066
            },
            "weekday_day": {
                "avg_time_sec": 30,
                "data_points": 8709
            },
            "weekday_offpeak": {
                "avg_time_sec": 30,
                "data_points": 16087
            },
            "weekend": {
                "avg_time_sec": 30,
                "data_points": 13288
            }
        },
        "3082O00047C0_3082O00027C0": {
            "weekday_evening_peak": {
                "avg_time_sec": 31,
                "data_points": 2
            },
            "weekend": {
                "avg_time_sec": 28,
                "data_points": 2
            },
            "weekday_day": {
                "avg_time_sec": 30,
                "data_points": 4
            }
        },
        "3082O00027C0_3082O00019C0": {
            "weekday_evening_peak": {
                "avg_time_sec": 29,
                "data_points": 7474
            },
            "weekday_day": {
                "avg_time_sec": 29,
                "data_points": 10913
            },
            "weekday_morning_peak": {
                "avg_time_sec": 29,
                "data_points": 2202
            },
            "weekday_offpeak": {
                "avg_time_sec": 29,
                "data_points": 17940
            },
            "weekend": {
                "avg_time_sec": 29,
                "data_points": 17222
            }
        },
        "3063O00006C0_3063O00007C0": {
            "weekday_day": {
                "avg_time_sec": 30,
                "data_points": 1914
            },
            "weekday_morning_peak": {
                "avg_time_sec": 30,
                "data_points": 558
            },
            "weekday_evening_peak": {
                "avg_time_sec": 30,
                "data_points": 1283
            },
            "weekend": {
                "avg_time_sec": 30,
                "data_points": 4382
            },
            "weekday_offpeak": {
                "avg_time_sec": 30,
                "data_points": 2099
            }
        },
        "3063O00007C0_3063O00008C0": {
            "weekday_day": {
                "avg_time_sec": 29,
                "data_points": 1583
            },
            "weekday_evening_peak": {
                "avg_time_sec": 30,
                "data_points": 1409
            },
            "weekday_morning_peak": {
                "avg_time_sec": 29,
                "data_points": 407
            },
            "weekday_offpeak": {
                "avg_time_sec": 29,
                "data_points": 1810
            },
            "weekend": {
                "avg_time_sec": 29,
                "data_points": 4577
            }
        },
        "3079O00020C0_3082O00046C0": {
            "weekday_day": {
                "avg_time_sec": 29,
                "data_points": 4838
            },
            "weekday_offpeak": {
                "avg_time_sec": 30,
                "data_points": 3647
            },
            "weekday_morning_peak": {
                "avg_time_sec": 30,
                "data_points": 446
            },
            "weekday_evening_peak": {
                "avg_time_sec": 29,
                "data_points": 3420
            },
            "weekend": {
                "avg_time_sec": 29,
                "data_points": 4377
            }
        },
        "3063O00050C1_3063O00066P0": {
            "weekday_evening_peak": {
                "avg_time_sec": 29,
                "data_points": 1386
            },
            "weekday_day": {
                "avg_time_sec": 28,
                "data_points": 1185
            },
            "weekday_offpeak": {
                "avg_time_sec": 29,
                "data_points": 1134
            },
            "weekday_morning_peak": {
                "avg_time_sec": 29,
                "data_points": 584
            },
            "weekend": {
                "avg_time_sec": 29,
                "data_points": 2980
            }
        },
        "3063O00008C0_3063O00010C0": {
            "weekday_evening_peak": {
                "avg_time_sec": 30,
                "data_points": 1435
            },
            "weekday_morning_peak": {
                "avg_time_sec": 36,
                "data_points": 400
            },
            "weekday_day": {
                "avg_time_sec": 30,
                "data_points": 1901
            },
            "weekday_offpeak": {
                "avg_time_sec": 30,
                "data_points": 2024
            },
            "weekend": {
                "avg_time_sec": 29,
                "data_points": 5084
            }
        },
        "3066O00004C0_3066O00005C0": {
            "weekday_evening_peak": {
                "avg_time_sec": 30,
                "data_points": 2601
            },
            "weekday_morning_peak": {
                "avg_time_sec": 30,
                "data_points": 1331
            },
            "weekday_day": {
                "avg_time_sec": 30,
                "data_points": 6337
            },
            "weekend": {
                "avg_time_sec": 30,
                "data_points": 8248
            },
            "weekday_offpeak": {
                "avg_time_sec": 30,
                "data_points": 7172
            }
        },
        "3082O00048C0_3082O00027C0": {
            "weekday_evening_peak": {
                "avg_time_sec": 30,
                "data_points": 6155
            },
            "weekday_morning_peak": {
                "avg_time_sec": 30,
                "data_points": 1899
            },
            "weekday_offpeak": {
                "avg_time_sec": 30,
                "data_points": 14398
            },
            "weekday_day": {
                "avg_time_sec": 30,
                "data_points": 9165
            },
            "weekend": {
                "avg_time_sec": 29,
                "data_points": 14901
            }
        },
        "3066O00005C0_3066O00007C9": {
            "weekday_day": {
                "avg_time_sec": 29,
                "data_points": 6330
            },
            "weekday_evening_peak": {
                "avg_time_sec": 30,
                "data_points": 3006
            },
            "weekday_morning_peak": {
                "avg_time_sec": 29,
                "data_points": 1413
            },
            "weekend": {
                "avg_time_sec": 29,
                "data_points": 8129
            },
            "weekday_offpeak": {
                "avg_time_sec": 30,
                "data_points": 7849
            }
        },
        "3071O00010C0_3071O00011C0": {
            "weekday_offpeak": {
                "avg_time_sec": 30,
                "data_points": 219
            },
            "weekday_day": {
                "avg_time_sec": 28,
                "data_points": 808
            },
            "weekday_morning_peak": {
                "avg_time_sec": 29,
                "data_points": 1109
            },
            "weekend": {
                "avg_time_sec": 26,
                "data_points": 131
            },
            "weekday_evening_peak": {
                "avg_time_sec": 29,
                "data_points": 511
            }
        },
        "3071O00035C0_3071O00012C0": {
            "weekday_offpeak": {
                "avg_time_sec": 30,
                "data_points": 139
            },
            "weekday_day": {
                "avg_time_sec": 28,
                "data_points": 1026
            },
            "weekday_morning_peak": {
                "avg_time_sec": 30,
                "data_points": 1969
            },
            "weekend": {
                "avg_time_sec": 29,
                "data_points": 589
            },
            "weekday_evening_peak": {
                "avg_time_sec": 30,
                "data_points": 937
            }
        },
        "3068O00003C0_3068O00004C0": {
            "weekday_offpeak": {
                "avg_time_sec": 29,
                "data_points": 841
            },
            "weekday_day": {
                "avg_time_sec": 28,
                "data_points": 1571
            },
            "weekday_morning_peak": {
                "avg_time_sec": 30,
                "data_points": 3505
            },
            "weekday_evening_peak": {
                "avg_time_sec": 30,
                "data_points": 1521
            },
            "weekend": {
                "avg_time_sec": 29,
                "data_points": 3173
            }
        },
        "3068O00004C0_3066O00061C0": {
            "weekday_offpeak": {
                "avg_time_sec": 30,
                "data_points": 783
            },
            "weekday_day": {
                "avg_time_sec": 30,
                "data_points": 1443
            },
            "weekday_morning_peak": {
                "avg_time_sec": 34,
                "data_points": 2895
            },
            "weekend": {
                "avg_time_sec": 30,
                "data_points": 2725
            },
            "weekday_evening_peak": {
                "avg_time_sec": 30,
                "data_points": 1678
            }
        },
        "3082O00064P0_3082O00007C0": {
            "weekday_offpeak": {
                "avg_time_sec": 29,
                "data_points": 2
            },
            "weekday_day": {
                "avg_time_sec": 42,
                "data_points": 2
            },
            "weekend": {
                "avg_time_sec": 32,
                "data_points": 6
            },
            "weekday_morning_peak": {
                "avg_time_sec": 22,
                "data_points": 2
            },
            "weekday_evening_peak": {
                "avg_time_sec": 31,
                "data_points": 1
            }
        },
        "3080O00015C0_3082O00029C0": {
            "weekday_offpeak": {
                "avg_time_sec": 28,
                "data_points": 119
            },
            "weekday_day": {
                "avg_time_sec": 30,
                "data_points": 622
            },
            "weekday_morning_peak": {
                "avg_time_sec": 29,
                "data_points": 1044
            },
            "weekend": {
                "avg_time_sec": 29,
                "data_points": 338
            },
            "weekday_evening_peak": {
                "avg_time_sec": 30,
                "data_points": 596
            }
        },
        "3056O00021C0_3056O00024C0": {
            "weekday_offpeak": {
                "avg_time_sec": 32,
                "data_points": 195
            },
            "weekday_day": {
                "avg_time_sec": 28,
                "data_points": 698
            },
            "weekday_morning_peak": {
                "avg_time_sec": 29,
                "data_points": 1131
            },
            "weekend": {
                "avg_time_sec": 29,
                "data_points": 80
            },
            "weekday_evening_peak": {
                "avg_time_sec": 29,
                "data_points": 457
            }
        },
        "3063O00066P0_3063O00040C0": {
            "weekday_morning_peak": {
                "avg_time_sec": 113,
                "data_points": 1335
            },
            "weekday_evening_peak": {
                "avg_time_sec": 42,
                "data_points": 2424
            },
            "weekday_offpeak": {
                "avg_time_sec": 59,
                "data_points": 2802
            },
            "weekday_day": {
                "avg_time_sec": 80,
                "data_points": 2650
            },
            "weekend": {
                "avg_time_sec": 30,
                "data_points": 5007
            }
        },
        "3063O00005C0_3063O00006C0": {
            "weekday_morning_peak": {
                "avg_time_sec": 30,
                "data_points": 582
            },
            "weekday_evening_peak": {
                "avg_time_sec": 30,
                "data_points": 1302
            },
            "weekday_day": {
                "avg_time_sec": 30,
                "data_points": 1979
            },
            "weekend": {
                "avg_time_sec": 27,
                "data_points": 3384
            },
            "weekday_offpeak": {
                "avg_time_sec": 29,
                "data_points": 2255
            }
        },
        "3063O00042C0_3063O00012C0": {
            "weekday_morning_peak": {
                "avg_time_sec": 57,
                "data_points": 1120
            },
            "weekday_day": {
                "avg_time_sec": 61,
                "data_points": 4818
            },
            "weekday_evening_peak": {
                "avg_time_sec": 60,
                "data_points": 2181
            },
            "weekday_offpeak": {
                "avg_time_sec": 30,
                "data_points": 4886
            },
            "weekend": {
                "avg_time_sec": 30,
                "data_points": 6867
            }
        },
        "3063O00012C0_3066O00004C0": {
            "weekday_morning_peak": {
                "avg_time_sec": 30,
                "data_points": 864
            },
            "weekday_day": {
                "avg_time_sec": 30,
                "data_points": 4206
            },
            "weekday_evening_peak": {
                "avg_time_sec": 39,
                "data_points": 1564
            },
            "weekend": {
                "avg_time_sec": 30,
                "data_points": 3955
            },
            "weekday_offpeak": {
                "avg_time_sec": 29,
                "data_points": 4139
            }
        },
        "3067O00001C0_3067O00002C0": {
            "weekday_morning_peak": {
                "avg_time_sec": 29,
                "data_points": 1492
            },
            "weekday_day": {
                "avg_time_sec": 28,
                "data_points": 7715
            },
            "weekday_evening_peak": {
                "avg_time_sec": 29,
                "data_points": 3718
            },
            "weekday_offpeak": {
                "avg_time_sec": 29,
                "data_points": 9260
            },
            "weekend": {
                "avg_time_sec": 29,
                "data_points": 8660
            }
        },
        "3069O00048C0_3069O00049C0": {
            "weekday_morning_peak": {
                "avg_time_sec": 29,
                "data_points": 1807
            },
            "weekday_day": {
                "avg_time_sec": 29,
                "data_points": 9344
            },
            "weekday_evening_peak": {
                "avg_time_sec": 29,
                "data_points": 4971
            },
            "weekday_offpeak": {
                "avg_time_sec": 29,
                "data_points": 13846
            },
            "weekend": {
                "avg_time_sec": 29,
                "data_points": 12640
            }
        },
        "3069O00029C0_3069O00030C0": {
            "weekday_morning_peak": {
                "avg_time_sec": 29,
                "data_points": 1877
            },
            "weekday_day": {
                "avg_time_sec": 30,
                "data_points": 9641
            },
            "weekday_offpeak": {
                "avg_time_sec": 30,
                "data_points": 13679
            },
            "weekday_evening_peak": {
                "avg_time_sec": 29,
                "data_points": 5688
            },
            "weekend": {
                "avg_time_sec": 29,
                "data_points": 13661
            }
        },
        "p35k_3079O00036C0": {
            "weekday_morning_peak": {
                "avg_time_sec": 30,
                "data_points": 1908
            },
            "weekday_day": {
                "avg_time_sec": 30,
                "data_points": 10066
            },
            "weekday_evening_peak": {
                "avg_time_sec": 30,
                "data_points": 4948
            },
            "weekday_offpeak": {
                "avg_time_sec": 30,
                "data_points": 12107
            },
            "weekend": {
                "avg_time_sec": 28,
                "data_points": 12166
            }
        },
        "3079O00035C0_3079O00019C0": {
            "weekday_morning_peak": {
                "avg_time_sec": 30,
                "data_points": 922
            },
            "weekday_day": {
                "avg_time_sec": 30,
                "data_points": 3774
            },
            "weekday_evening_peak": {
                "avg_time_sec": 29,
                "data_points": 2912
            },
            "weekday_offpeak": {
                "avg_time_sec": 30,
                "data_points": 913
            },
            "weekend": {
                "avg_time_sec": 28,
                "data_points": 1963
            }
        },
        "3079O00019C0_3079O00020C0": {
            "weekday_morning_peak": {
                "avg_time_sec": 28,
                "data_points": 315
            },
            "weekday_day": {
                "avg_time_sec": 28,
                "data_points": 3481
            },
            "weekday_evening_peak": {
                "avg_time_sec": 29,
                "data_points": 2662
            },
            "weekend": {
                "avg_time_sec": 28,
                "data_points": 2352
            },
            "weekday_offpeak": {
                "avg_time_sec": 29,
                "data_points": 1596
            }
        },
        "3082O00047C0_3082O00048C0": {
            "weekday_morning_peak": {
                "avg_time_sec": 29,
                "data_points": 1839
            },
            "weekday_day": {
                "avg_time_sec": 29,
                "data_points": 7669
            },
            "weekday_evening_peak": {
                "avg_time_sec": 29,
                "data_points": 6415
            },
            "weekday_offpeak": {
                "avg_time_sec": 29,
                "data_points": 13342
            },
            "weekend": {
                "avg_time_sec": 30,
                "data_points": 12843
            }
        },
        "3080O00018C0_3056O00021C0": {
            "weekday_day": {
                "avg_time_sec": 61,
                "data_points": 1
            },
            "weekday_offpeak": {
                "avg_time_sec": 60,
                "data_points": 1
            }
        },
        "3062O00076C0_3062O00007C0": {
            "weekday_day": {
                "avg_time_sec": 29,
                "data_points": 1171
            },
            "weekday_offpeak": {
                "avg_time_sec": 30,
                "data_points": 749
            },
            "weekday_evening_peak": {
                "avg_time_sec": 30,
                "data_points": 408
            },
            "weekday_morning_peak": {
                "avg_time_sec": 30,
                "data_points": 313
            },
            "weekend": {
                "avg_time_sec": 30,
                "data_points": 779
            }
        },
        "3062O00007C0_3062O00008C0": {
            "weekday_day": {
                "avg_time_sec": 29,
                "data_points": 1480
            },
            "weekday_morning_peak": {
                "avg_time_sec": 30,
                "data_points": 388
            },
            "weekday_evening_peak": {
                "avg_time_sec": 30,
                "data_points": 502
            },
            "weekday_offpeak": {
                "avg_time_sec": 30,
                "data_points": 1447
            },
            "weekend": {
                "avg_time_sec": 30,
                "data_points": 1191
            }
        },
        "3062O00008C0_3062O00009C0": {
            "weekday_day": {
                "avg_time_sec": 30,
                "data_points": 1756
            },
            "weekend": {
                "avg_time_sec": 29,
                "data_points": 1462
            },
            "weekday_morning_peak": {
                "avg_time_sec": 30,
                "data_points": 455
            },
            "weekday_evening_peak": {
                "avg_time_sec": 30,
                "data_points": 644
            },
            "weekday_offpeak": {
                "avg_time_sec": 30,
                "data_points": 1615
            }
        },
        "3062O00009C0_3062O00010C0": {
            "weekday_day": {
                "avg_time_sec": 30,
                "data_points": 1958
            },
            "weekday_evening_peak": {
                "avg_time_sec": 31,
                "data_points": 589
            },
            "weekday_morning_peak": {
                "avg_time_sec": 33,
                "data_points": 498
            },
            "weekend": {
                "avg_time_sec": 29,
                "data_points": 1653
            },
            "weekday_offpeak": {
                "avg_time_sec": 30,
                "data_points": 1782
            }
        },
        "3062O00010C0_3062O00013C0": {
            "weekday_day": {
                "avg_time_sec": 91,
                "data_points": 2208
            },
            "weekday_evening_peak": {
                "avg_time_sec": 101,
                "data_points": 757
            },
            "weekday_morning_peak": {
                "avg_time_sec": 99,
                "data_points": 558
            },
            "weekend": {
                "avg_time_sec": 45,
                "data_points": 1991
            },
            "weekday_offpeak": {
                "avg_time_sec": 36,
                "data_points": 2298
            }
        },
        "3062O00013C0_3063O00041C0": {
            "weekday_day": {
                "avg_time_sec": 30,
                "data_points": 2208
            },
            "weekday_evening_peak": {
                "avg_time_sec": 30,
                "data_points": 595
            },
            "weekday_morning_peak": {
                "avg_time_sec": 30,
                "data_points": 457
            },
            "weekend": {
                "avg_time_sec": 30,
                "data_points": 1661
            },
            "weekday_offpeak": {
                "avg_time_sec": 30,
                "data_points": 1931
            }
        },
        "3063O00057C0_3063O00042C0": {
            "weekday_day": {
                "avg_time_sec": 28,
                "data_points": 3099
            },
            "weekday_evening_peak": {
                "avg_time_sec": 30,
                "data_points": 896
            },
            "weekday_morning_peak": {
                "avg_time_sec": 29,
                "data_points": 674
            },
            "weekend": {
                "avg_time_sec": 29,
                "data_points": 2085
            },
            "weekday_offpeak": {
                "avg_time_sec": 29,
                "data_points": 2044
            }
        },
        "3079O00036C0_3079O00035C0": {
            "weekday_day": {
                "avg_time_sec": 29,
                "data_points": 5674
            },
            "weekday_morning_peak": {
                "avg_time_sec": 29,
                "data_points": 1078
            },
            "weekday_evening_peak": {
                "avg_time_sec": 29,
                "data_points": 3162
            },
            "weekday_offpeak": {
                "avg_time_sec": 29,
                "data_points": 1706
            },
            "weekend": {
                "avg_time_sec": 27,
                "data_points": 2140
            }
        },
        "3063O00040C0_3063O00005C0": {
            "weekday_evening_peak": {
                "avg_time_sec": 71,
                "data_points": 495
            },
            "weekday_day": {
                "avg_time_sec": 58,
                "data_points": 457
            },
            "weekend": {
                "avg_time_sec": 35,
                "data_points": 1928
            },
            "weekday_morning_peak": {
                "avg_time_sec": 80,
                "data_points": 112
            },
            "weekday_offpeak": {
                "avg_time_sec": 40,
                "data_points": 1672
            }
        },
        "3069O00031C0_p35k": {
            "weekday_evening_peak": {
                "avg_time_sec": 62,
                "data_points": 1
            },
            "weekday_day": {
                "avg_time_sec": 50,
                "data_points": 12
            }
        },
        "3079O00035C0_3079O00020C0": {
            "weekday_evening_peak": {
                "avg_time_sec": 27,
                "data_points": 2
            },
            "weekday_day": {
                "avg_time_sec": 33,
                "data_points": 6
            },
            "weekend": {
                "avg_time_sec": 22,
                "data_points": 1
            }
        },
        "3069O00030C0_3079O00034C0": {
            "weekday_offpeak": {
                "avg_time_sec": 92,
                "data_points": 1
            },
            "weekday_day": {
                "avg_time_sec": 30,
                "data_points": 4
            }
        },
        "3079O00036C0_3079O00019C0": {
            "weekday_offpeak": {
                "avg_time_sec": 30,
                "data_points": 1
            },
            "weekday_day": {
                "avg_time_sec": 26,
                "data_points": 6
            },
            "weekday_evening_peak": {
                "avg_time_sec": 23,
                "data_points": 1
            },
            "weekend": {
                "avg_time_sec": 19,
                "data_points": 4
            }
        },
        "3066O00061C0_3066O00002C9": {
            "weekday_day": {
                "avg_time_sec": 30,
                "data_points": 935
            },
            "weekday_offpeak": {
                "avg_time_sec": 29,
                "data_points": 467
            },
            "weekday_morning_peak": {
                "avg_time_sec": 29,
                "data_points": 1405
            },
            "weekend": {
                "avg_time_sec": 29,
                "data_points": 1415
            },
            "weekday_evening_peak": {
                "avg_time_sec": 30,
                "data_points": 814
            }
        },
        "3080O00018C0_3056O00024C0": {
            "weekday_offpeak": {
                "avg_time_sec": 61,
                "data_points": 1
            }
        },
        "3066O00002C9_3066O00055C0": {
            "weekday_offpeak": {
                "avg_time_sec": 29,
                "data_points": 588
            },
            "weekday_day": {
                "avg_time_sec": 29,
                "data_points": 764
            },
            "weekend": {
                "avg_time_sec": 29,
                "data_points": 1194
            },
            "weekday_evening_peak": {
                "avg_time_sec": 30,
                "data_points": 529
            },
            "weekday_morning_peak": {
                "avg_time_sec": 30,
                "data_points": 745
            }
        },
        "3066O00056C0_3064O00016C0": {
            "weekday_offpeak": {
                "avg_time_sec": 30,
                "data_points": 377
            },
            "weekday_day": {
                "avg_time_sec": 30,
                "data_points": 734
            },
            "weekday_evening_peak": {
                "avg_time_sec": 30,
                "data_points": 561
            },
            "weekend": {
                "avg_time_sec": 30,
                "data_points": 1064
            },
            "weekday_morning_peak": {
                "avg_time_sec": 30,
                "data_points": 371
            }
        },
        "3064O00016C0_3064O00001C0": {
            "weekday_offpeak": {
                "avg_time_sec": 30,
                "data_points": 648
            },
            "weekday_day": {
                "avg_time_sec": 53,
                "data_points": 1190
            },
            "weekday_morning_peak": {
                "avg_time_sec": 37,
                "data_points": 773
            },
            "weekend": {
                "avg_time_sec": 30,
                "data_points": 1717
            },
            "weekday_evening_peak": {
                "avg_time_sec": 31,
                "data_points": 1151
            }
        },
        "p35k_3079O00019C0": {
            "weekday_morning_peak": {
                "avg_time_sec": 92,
                "data_points": 1
            },
            "weekday_day": {
                "avg_time_sec": 30,
                "data_points": 1
            }
        },
        "3080O00013C0_3056O00024C0": {
            "weekday_morning_peak": {
                "avg_time_sec": 30,
                "data_points": 1
            },
            "weekday_day": {
                "avg_time_sec": 30,
                "data_points": 2
            },
            "weekend": {
                "avg_time_sec": 30,
                "data_points": 2
            },
            "weekday_offpeak": {
                "avg_time_sec": 31,
                "data_points": 1
            }
        },
        "3071O00010C0_3071O00035C0": {
            "weekday_morning_peak": {
                "avg_time_sec": 30,
                "data_points": 2
            },
            "weekday_evening_peak": {
                "avg_time_sec": 30,
                "data_points": 4
            }
        },
        "3063O00007C0_3063O00010C0": {
            "weekday_morning_peak": {
                "avg_time_sec": 122,
                "data_points": 1
            }
        },
        "3063O00041C0_3063O00057C0": {
            "weekday_morning_peak": {
                "avg_time_sec": 28,
                "data_points": 420
            },
            "weekday_day": {
                "avg_time_sec": 29,
                "data_points": 2484
            },
            "weekday_evening_peak": {
                "avg_time_sec": 30,
                "data_points": 706
            },
            "weekend": {
                "avg_time_sec": 29,
                "data_points": 1317
            },
            "weekday_offpeak": {
                "avg_time_sec": 30,
                "data_points": 1246
            }
        },
        "3066O00011C9_3066O00012C0": {
            "weekday_morning_peak": {
                "avg_time_sec": 93,
                "data_points": 1
            },
            "weekend": {
                "avg_time_sec": 80,
                "data_points": 4
            },
            "weekday_day": {
                "avg_time_sec": 92,
                "data_points": 4
            }
        },
        "3067O00012C0_3067O00002C0": {
            "weekday_morning_peak": {
                "avg_time_sec": 30,
                "data_points": 1
            },
            "weekday_offpeak": {
                "avg_time_sec": 30,
                "data_points": 1
            },
            "weekday_day": {
                "avg_time_sec": 31,
                "data_points": 5
            }
        },
        "3079O00020C0_3082O00019C0": {
            "weekday_day": {
                "avg_time_sec": 291,
                "data_points": 1
            }
        },
        "3066O00055C0_3066O00056C0": {
            "weekday_day": {
                "avg_time_sec": 30,
                "data_points": 989
            },
            "weekday_evening_peak": {
                "avg_time_sec": 31,
                "data_points": 448
            },
            "weekday_offpeak": {
                "avg_time_sec": 30,
                "data_points": 503
            },
            "weekend": {
                "avg_time_sec": 30,
                "data_points": 1159
            },
            "weekday_morning_peak": {
                "avg_time_sec": 38,
                "data_points": 288
            }
        },
        "3063O00067C0_3063O00054C0": {
            "weekday_evening_peak": {
                "avg_time_sec": 29,
                "data_points": 221
            },
            "weekday_day": {
                "avg_time_sec": 29,
                "data_points": 325
            },
            "weekday_offpeak": {
                "avg_time_sec": 30,
                "data_points": 452
            },
            "weekday_morning_peak": {
                "avg_time_sec": 30,
                "data_points": 51
            },
            "weekend": {
                "avg_time_sec": 30,
                "data_points": 315
            }
        },
        "3082O00029C0_3080O00018C0": {
            "weekday_offpeak": {
                "avg_time_sec": 31,
                "data_points": 2
            },
            "weekday_morning_peak": {
                "avg_time_sec": 30,
                "data_points": 2
            },
            "weekday_day": {
                "avg_time_sec": 31,
                "data_points": 1
            }
        },
        "3063O00066P0_3063O00006C0": {
            "weekday_offpeak": {
                "avg_time_sec": 710,
                "data_points": 1
            }
        },
        "3066O00051C0_3068O00017C0": {
            "weekday_day": {
                "avg_time_sec": 83,
                "data_points": 210
            },
            "weekend": {
                "avg_time_sec": 60,
                "data_points": 6
            },
            "weekday_evening_peak": {
                "avg_time_sec": 59,
                "data_points": 2
            },
            "weekday_offpeak": {
                "avg_time_sec": 62,
                "data_points": 1
            }
        },
        "3082O00064P0_3082O00011C0": {
            "weekday_offpeak": {
                "avg_time_sec": 185,
                "data_points": 1
            },
            "weekend": {
                "avg_time_sec": 42,
                "data_points": 2
            }
        },
        "3062O00012C0_3062O00076C0": {
            "weekday_day": {
                "avg_time_sec": 29,
                "data_points": 1064
            },
            "weekend": {
                "avg_time_sec": 29,
                "data_points": 796
            },
            "weekday_evening_peak": {
                "avg_time_sec": 29,
                "data_points": 417
            },
            "weekday_morning_peak": {
                "avg_time_sec": 28,
                "data_points": 309
            },
            "weekday_offpeak": {
                "avg_time_sec": 30,
                "data_points": 744
            }
        },
        "3063O00004C0_3063O00040C0": {
            "weekday_day": {
                "avg_time_sec": 154,
                "data_points": 1
            }
        },
        "3068O00017C0_3068O00019C0": {
            "weekday_evening_peak": {
                "avg_time_sec": 30,
                "data_points": 1
            },
            "weekend": {
                "avg_time_sec": 30,
                "data_points": 1
            }
        },
        "3079O00020C0_3082O00047C0": {
            "weekday_evening_peak": {
                "avg_time_sec": 40,
                "data_points": 2
            }
        },
        "3082O00006C0_3082O00011C0": {
            "weekday_offpeak": {
                "avg_time_sec": 31,
                "data_points": 1
            },
            "weekend": {
                "avg_time_sec": 31,
                "data_points": 1
            }
        },
        "3062O00006C0_3062O00012C0": {
            "weekday_day": {
                "avg_time_sec": 30,
                "data_points": 691
            },
            "weekday_morning_peak": {
                "avg_time_sec": 30,
                "data_points": 231
            },
            "weekday_evening_peak": {
                "avg_time_sec": 29,
                "data_points": 294
            },
            "weekday_offpeak": {
                "avg_time_sec": 30,
                "data_points": 945
            },
            "weekend": {
                "avg_time_sec": 30,
                "data_points": 756
            }
        },
        "3063O00010C0_3063O00067C0": {
            "weekday_day": {
                "avg_time_sec": 47,
                "data_points": 11
            },
            "weekend": {
                "avg_time_sec": 31,
                "data_points": 1
            },
            "weekday_evening_peak": {
                "avg_time_sec": 30,
                "data_points": 2
            },
            "weekday_morning_peak": {
                "avg_time_sec": 23,
                "data_points": 3
            }
        },
        "3063O00038C0_3063O00067C0": {
            "weekday_evening_peak": {
                "avg_time_sec": 30,
                "data_points": 680
            },
            "weekday_day": {
                "avg_time_sec": 29,
                "data_points": 987
            },
            "weekday_morning_peak": {
                "avg_time_sec": 29,
                "data_points": 340
            },
            "weekday_offpeak": {
                "avg_time_sec": 30,
                "data_points": 2245
            },
            "weekend": {
                "avg_time_sec": 30,
                "data_points": 2247
            }
        },
        "3082O00007C0_3082O00012C0": {
            "weekend": {
                "avg_time_sec": 27,
                "data_points": 3
            },
            "weekday_day": {
                "avg_time_sec": 21,
                "data_points": 1
            },
            "weekday_offpeak": {
                "avg_time_sec": 24,
                "data_points": 2
            }
        },
        "3063O00054C0_3063O00055C0": {
            "weekend": {
                "avg_time_sec": 30,
                "data_points": 188
            },
            "weekday_day": {
                "avg_time_sec": 29,
                "data_points": 240
            },
            "weekday_morning_peak": {
                "avg_time_sec": 30,
                "data_points": 44
            },
            "weekday_evening_peak": {
                "avg_time_sec": 30,
                "data_points": 63
            },
            "weekday_offpeak": {
                "avg_time_sec": 30,
                "data_points": 271
            }
        },
        "3069O00049C0_3069O00029C0": {
            "weekend": {
                "avg_time_sec": 31,
                "data_points": 1
            },
            "weekday_morning_peak": {
                "avg_time_sec": 31,
                "data_points": 1
            },
            "weekday_evening_peak": {
                "avg_time_sec": 31,
                "data_points": 2
            },
            "weekday_day": {
                "avg_time_sec": 30,
                "data_points": 3
            }
        },
        "3063O00005C0_3063O00007C0": {
            "weekend": {
                "avg_time_sec": 31,
                "data_points": 2
            },
            "weekday_offpeak": {
                "avg_time_sec": 18,
                "data_points": 1
            }
        },
        "3063O00010C0_3063O00038C0": {
            "weekend": {
                "avg_time_sec": 30,
                "data_points": 2024
            },
            "weekday_evening_peak": {
                "avg_time_sec": 30,
                "data_points": 598
            },
            "weekday_day": {
                "avg_time_sec": 29,
                "data_points": 699
            },
            "weekday_offpeak": {
                "avg_time_sec": 30,
                "data_points": 1966
            },
            "weekday_morning_peak": {
                "avg_time_sec": 30,
                "data_points": 287
            }
        },
        "3071O00011C0_3071O00012C0": {
            "weekend": {
                "avg_time_sec": 22,
                "data_points": 3
            }
        },
        "3071O00009C0_3071O00011C0": {
            "weekend": {
                "avg_time_sec": 30,
                "data_points": 1
            },
            "weekday_offpeak": {
                "avg_time_sec": 31,
                "data_points": 1
            },
            "weekday_morning_peak": {
                "avg_time_sec": 30,
                "data_points": 1
            }
        },
        "3066O00008C9_3066O00011C9": {
            "weekend": {
                "avg_time_sec": 31,
                "data_points": 1
            }
        },
        "3063O00020C0_3063O00050C1": {
            "weekday_morning_peak": {
                "avg_time_sec": 89,
                "data_points": 45
            },
            "weekday_day": {
                "avg_time_sec": 110,
                "data_points": 147
            },
            "weekday_evening_peak": {
                "avg_time_sec": 86,
                "data_points": 465
            },
            "weekend": {
                "avg_time_sec": 38,
                "data_points": 1459
            },
            "weekday_offpeak": {
                "avg_time_sec": 81,
                "data_points": 722
            }
        },
        "3067O00002C0_3069O00004C0": {
            "weekday_morning_peak": {
                "avg_time_sec": 28,
                "data_points": 2
            },
            "weekday_day": {
                "avg_time_sec": 30,
                "data_points": 5
            },
            "weekday_evening_peak": {
                "avg_time_sec": 30,
                "data_points": 1
            },
            "weekend": {
                "avg_time_sec": 15,
                "data_points": 1
            }
        },
        "3082O00064P0_3082O00012C0": {
            "weekday_morning_peak": {
                "avg_time_sec": 54,
                "data_points": 1
            }
        },
        "3080O00006C0_3056O00021C0": {
            "weekday_day": {
                "avg_time_sec": 77,
                "data_points": 1
            }
        },
        "3063O00056C0_3062O00006C0": {
            "weekday_day": {
                "avg_time_sec": 29,
                "data_points": 776
            },
            "weekday_evening_peak": {
                "avg_time_sec": 28,
                "data_points": 321
            },
            "weekday_morning_peak": {
                "avg_time_sec": 30,
                "data_points": 222
            },
            "weekday_offpeak": {
                "avg_time_sec": 30,
                "data_points": 677
            },
            "weekend": {
                "avg_time_sec": 30,
                "data_points": 635
            }
        },
        "3067O00002C0_3069O00005C0": {
            "weekday_evening_peak": {
                "avg_time_sec": 31,
                "data_points": 1
            }
        },
        "3062O00013C0_3063O00057C0": {
            "weekday_evening_peak": {
                "avg_time_sec": 31,
                "data_points": 1
            },
            "weekday_morning_peak": {
                "avg_time_sec": 18,
                "data_points": 1
            }
        },
        "3063O00004C0_3063O00020C0": {
            "weekday_day": {
                "avg_time_sec": 34,
                "data_points": 27
            },
            "weekday_morning_peak": {
                "avg_time_sec": 30,
                "data_points": 19
            },
            "weekend": {
                "avg_time_sec": 43,
                "data_points": 366
            },
            "weekday_offpeak": {
                "avg_time_sec": 30,
                "data_points": 80
            },
            "weekday_evening_peak": {
                "avg_time_sec": 30,
                "data_points": 214
            }
        },
        "3066O00007C9_3066O00010C9": {
            "weekday_day": {
                "avg_time_sec": 31,
                "data_points": 1
            },
            "weekend": {
                "avg_time_sec": 102,
                "data_points": 2
            }
        },
        "3066O00007C9_3068O00019C0": {
            "weekday_morning_peak": {
                "avg_time_sec": 105,
                "data_points": 1
            }
        },
        "3079O00036C0_3079O00020C0": {
            "weekday_day": {
                "avg_time_sec": 31,
                "data_points": 1
            }
        },
        "3069O00029C0_3069O00031C0": {
            "weekday_day": {
                "avg_time_sec": 31,
                "data_points": 5
            }
        },
        "3079O00035C0_3082O00046C0": {
            "weekday_day": {
                "avg_time_sec": 26,
                "data_points": 1
            }
        },
        "3063O00067C0_3063O00055C0": {
            "weekday_evening_peak": {
                "avg_time_sec": 31,
                "data_points": 1
            }
        },
        "3063O00054C0_3063O00056C0": {
            "weekday_morning_peak": {
                "avg_time_sec": 31,
                "data_points": 1
            },
            "weekday_day": {
                "avg_time_sec": 30,
                "data_points": 4
            }
        },
        "3056O00024C0_3071O00034C0": {
            "weekday_offpeak": {
                "avg_time_sec": 65,
                "data_points": 1
            },
            "weekend": {
                "avg_time_sec": 61,
                "data_points": 1
            }
        },
        "3068O00018C0_3068O00007C0": {
            "weekday_evening_peak": {
                "avg_time_sec": 61,
                "data_points": 1
            },
            "weekend": {
                "avg_time_sec": 31,
                "data_points": 1
            }
        },
        "3056O00021C0_3056O00005C0": {
            "weekend": {
                "avg_time_sec": 60,
                "data_points": 1
            }
        },
        "3066O00011C9_3068O00017C0": {
            "weekend": {
                "avg_time_sec": 171,
                "data_points": 1
            },
            "weekday_evening_peak": {
                "avg_time_sec": 123,
                "data_points": 1
            }
        },
        "3082O00046C0_3082O00048C0": {
            "weekend": {
                "avg_time_sec": 92,
                "data_points": 1
            }
        },
        "3063O00006C0_3063O00008C0": {
            "weekday_offpeak": {
                "avg_time_sec": 14,
                "data_points": 1
            }
        },
        "3071O00010C0_3071O00012C0": {
            "weekend": {
                "avg_time_sec": 30,
                "data_points": 1
            }
        },
        "3079O00034C0_3079O00020C0": {
            "weekend": {
                "avg_time_sec": 68,
                "data_points": 1
            }
        },
        "3063O00041C0_3063O00042C0": {
            "weekend": {
                "avg_time_sec": 31,
                "data_points": 1
            }
        },
        "3079O00034C0_3079O00036C0": {
            "weekend": {
                "avg_time_sec": 33,
                "data_points": 1
            }
        },
        "3063O00055C0_3063O00056C0": {
            "weekend": {
                "avg_time_sec": 29,
                "data_points": 231
            },
            "weekday_day": {
                "avg_time_sec": 30,
                "data_points": 322
            },
            "weekday_evening_peak": {
                "avg_time_sec": 30,
                "data_points": 82
            },
            "weekday_offpeak": {
                "avg_time_sec": 29,
                "data_points": 279
            },
            "weekday_morning_peak": {
                "avg_time_sec": 30,
                "data_points": 56
            }
        },
        "3067O00003C0_3069O00005C0": {
            "weekday_day": {
                "avg_time_sec": 61,
                "data_points": 8
            }
        },
        "3069O00006C0_3069O00049C0": {
            "weekday_day": {
                "avg_time_sec": 31,
                "data_points": 4
            }
        },
        "3067O00003C0_3069O00006C0": {
            "weekday_day": {
                "avg_time_sec": 62,
                "data_points": 4
            }
        },
        "3069O00004C0_3069O00006C0": {
            "weekday_day": {
                "avg_time_sec": 93,
                "data_points": 4
            }
        },
        "3082O00007C0_3082O00006C0": {
            "weekday_day": {
                "avg_time_sec": 31,
                "data_points": 12
            }
        },
        "3063O00010C0_3063O00054C0": {
            "weekday_day": {
                "avg_time_sec": 31,
                "data_points": 4
            }
        },
        "3082O00006C0_3082O00015C0": {
            "weekday_offpeak": {
                "avg_time_sec": 1258,
                "data_points": 14
            },
            "weekday_evening_peak": {
                "avg_time_sec": 1398,
                "data_points": 3
            },
            "weekday_day": {
                "avg_time_sec": 1576,
                "data_points": 36
            }
        }
    }
}